cli/client.py
cli/datasets.py
cli/helpers/__init__.py
cli/helpers/nucleus_url.py
cli/helpers/web_helper.py
cli/install_completion.py
cli/jobs.py
cli/models.py
cli/nu.py
cli/reference.py
cli/slices.py
cli/tests.py
nucleus/__init__.py
nucleus/annotation.py
nucleus/annotation_uploader.py
nucleus/async_job.py
nucleus/async_utils.py
nucleus/autocurate.py
nucleus/camera_params.py
nucleus/chip_utils.py
nucleus/connection.py
nucleus/constants.py
nucleus/data_transfer_object/__init__.py
nucleus/data_transfer_object/dataset_details.py
nucleus/data_transfer_object/dataset_info.py
nucleus/data_transfer_object/dataset_size.py
nucleus/data_transfer_object/job_status.py
nucleus/data_transfer_object/scenes_list.py
nucleus/dataset.py
nucleus/dataset_item.py
nucleus/dataset_item_uploader.py
nucleus/deprecation_warning.py
nucleus/embedding_index.py
nucleus/errors.py
nucleus/evaluation_match.py
nucleus/job.py
nucleus/logger.py
nucleus/metadata_manager.py
nucleus/metrics/__init__.py
nucleus/metrics/base.py
nucleus/metrics/categorization_metrics.py
nucleus/metrics/cuboid_metrics.py
nucleus/metrics/cuboid_utils.py
nucleus/metrics/custom_types.py
nucleus/metrics/errors.py
nucleus/metrics/filtering.py
nucleus/metrics/filters.py
nucleus/metrics/metric_utils.py
nucleus/metrics/polygon_metrics.py
nucleus/metrics/polygon_utils.py
nucleus/metrics/segmentation_loader.py
nucleus/metrics/segmentation_metrics.py
nucleus/metrics/segmentation_to_poly_metrics.py
nucleus/metrics/segmentation_utils.py
nucleus/model.py
nucleus/model_run.py
nucleus/package_not_installed.py
nucleus/payload_constructor.py
nucleus/prediction.py
nucleus/pydantic_base.py
nucleus/quaternion.py
nucleus/retry_strategy.py
nucleus/scene.py
nucleus/slice.py
nucleus/test_launch_integration.py
nucleus/track.py
nucleus/upload_response.py
nucleus/url_utils.py
nucleus/utils.py
nucleus/validate/__init__.py
nucleus/validate/client.py
nucleus/validate/constants.py
nucleus/validate/data_transfer_objects/__init__.py
scale_nucleus-0.17.11.dist-info/LICENSE
scale_nucleus-0.17.11.dist-info/METADATA
scale_nucleus-0.17.11.dist-info/WHEEL
scale_nucleus-0.17.11.dist-info/entry_points.txt
scale_nucleus-0.17.11.dist-info/RECORD
