Metadata-Version: 2.1
Name: scale-nucleus
Version: 0.17.11
Summary: The official Python client library for Nucleus, the Data Platform for AI
Home-page: https://scale.com/nucleus
License: MIT
Author: Scale AI Nucleus Team
Author-email: nucleusapi@scaleapi.com
Requires-Python: >=3.7,<4.0
Classifier: License :: OSI Approved :: MIT License
Classifier: Programming Language :: Python :: 3
Classifier: Programming Language :: Python :: 3.7
Classifier: Programming Language :: Python :: 3.8
Classifier: Programming Language :: Python :: 3.9
Classifier: Programming Language :: Python :: 3.10
Classifier: Programming Language :: Python :: 3.11
Provides-Extra: launch
Provides-Extra: metrics
Requires-Dist: Pillow (>=7.1.2)
Requires-Dist: Shapely (>=1.8.0) ; extra == "metrics"
Requires-Dist: aiohttp (>=3.7.4,<4.0.0)
Requires-Dist: boto3 (>=1.28.56,<2.0.0)
Requires-Dist: click (>=7.1.2,<9.0)
Requires-Dist: nest-asyncio (>=1.5.1,<2.0.0)
Requires-Dist: numpy (>=1.19.5) ; python_version >= "3.7" and python_version < "3.10"
Requires-Dist: numpy (>=1.22.0) ; python_version >= "3.10"
Requires-Dist: pydantic (>=1.8.2)
Requires-Dist: python-dateutil (>=2.8.2,<3.0.0)
Requires-Dist: questionary (>=1.10.0,<2.0.0)
Requires-Dist: rasterio (>=1.2.0) ; extra == "metrics"
Requires-Dist: requests (>=2.23.0,<3.0.0)
Requires-Dist: rich (>=10.15.2)
Requires-Dist: scale-launch (>=0.1.0) ; (python_version >= "3.7" and python_version < "4.0") and (extra == "launch")
Requires-Dist: scikit-learn (>=0.24.0) ; extra == "metrics"
Requires-Dist: scipy (>=1.4.1) ; extra == "metrics"
Requires-Dist: shellingham (>=1.4.0,<2.0.0)
Requires-Dist: tqdm (>=4.41.0,<5.0.0)
Project-URL: Documentation, https://dashboard.scale.com/nucleus/docs/api
Project-URL: Repository, https://github.com/scaleapi/nucleus-python-client
